caldav/__init__.py
caldav/_version.py
caldav/calendarobjectresource.py
caldav/collection.py
caldav/compatibility_hints.py
caldav/config.py
caldav/davclient.py
caldav/davobject.py
caldav/discovery.py
caldav/objects.py
caldav/py.typed
caldav/requests.py
caldav/search.py
caldav/elements/__init__.py
caldav/elements/base.py
caldav/elements/cdav.py
caldav/elements/dav.py
caldav/elements/ical.py
caldav/lib/__init__.py
caldav/lib/debug.py
caldav/lib/error.py
caldav/lib/namespace.py
caldav/lib/python_utilities.py
caldav/lib/url.py
caldav/lib/vcal.py
caldav-2.2.5.dist-info/METADATA
caldav-2.2.5.dist-info/WHEEL
caldav-2.2.5.dist-info/licenses/COPYING.APACHE
caldav-2.2.5.dist-info/licenses/COPYING.GPL
caldav-2.2.5.dist-info/RECORD
